trackr/__init__.py
trackr/cli.py
trackr/exceptions.py
trackr/main.py
trackr/carriers/__init__.py
trackr/carriers/base.py
trackr/carriers/fake.py
trackr/carriers/ect/__init__.py
trackr/carriers/ect/ect.py
trackr-2.3.0.dist-info/AUTHORS.rst
trackr-2.3.0.dist-info/LICENSE
trackr-2.3.0.dist-info/METADATA
trackr-2.3.0.dist-info/WHEEL
trackr-2.3.0.dist-info/entry_points.txt
trackr-2.3.0.dist-info/top_level.txt
trackr-2.3.0.dist-info/RECORD
