Metadata-Version: 2.1
Name: trackr
Version: 2.3.0
Summary: -
Home-page: https://github.com/rpedigoni/trackr
Author: Renato Pedigoni
Author-email: renatopedigoni@gmail.com
License: MIT license
Keywords: trackr
Classifier: Development Status :: 2 - Pre-Alpha
Classifier: Intended Audience :: Developers
Classifier: License :: OSI Approved :: MIT License
Classifier: Natural Language :: English
Classifier: Programming Language :: Python :: 2
Classifier: Programming Language :: Python :: 2.6
Classifier: Programming Language :: Python :: 2.7
Classifier: Programming Language :: Python :: 3
Classifier: Programming Language :: Python :: 3.3
Classifier: Programming Language :: Python :: 3.4
Classifier: Programming Language :: Python :: 3.5
License-File: LICENSE
License-File: AUTHORS.rst
Requires-Dist: click==8.1.7
Requires-Dist: colorama==0.4.6
Requires-Dist: zeep==4.3.1
Requires-Dist: requests
